pikatools/__init__.py
pikatools/__version__.py
pikatools/async_consumer.py
pikatools/async_publisher.py
pikatools/connection.py
pikatools/pool.py
pikatools/simple_async_consumer.py
pikatools/simple_async_publisher.py
pikatools-0.12.7.dist-info/LICENSE
pikatools-0.12.7.dist-info/METADATA
pikatools-0.12.7.dist-info/WHEEL
pikatools-0.12.7.dist-info/top_level.txt
pikatools-0.12.7.dist-info/RECORD
