Metadata-Version: 2.1
Name: pikatools
Version: 0.12.7
Summary: A collection of pika helpers.
Home-page: https://github.com/5uper5hoot/PikaTools
Author: Peter Schutt
Author-email: peter_schutt@bigpond.com
License: MIT
Platform: UNKNOWN
Classifier: License :: OSI Approved :: MIT License
Classifier: License :: OSI Approved :: BSD License
Classifier: Programming Language :: Python
Classifier: Programming Language :: Python :: 3 :: Only
Classifier: Programming Language :: Python :: 3.6
Classifier: Programming Language :: Python :: 3.7
Requires-Python: >=3.6.0
Requires-Dist: pika (~=0.12.0)
